{
  "Knob_Showcase_Gear_Advanced": {
    "type": "OcaBlock",
    "description": "50 Gear Knobs showcasing Teeth count, Monochrome styles, and varied Pointers.",
    "layout_columns": 5,
    "column_sizing": [
      {"weight": 1}, {"weight": 1}, {"weight": 1}, {"weight": 1}, {"weight": 1}
    ],
    "fields": {
      "gear_01": { "type": "_Knob", "label_active": "Mono 8T", "width": 100, "height": 100, "shape": "gear", "arc_width": 5, "indicator_color": "white", "knob_fill_color": "black", "knob_teeth": 8, "gradient_level": 0, "pointer_style": "line", "show_ticks": true, "tick_style": "simple" },
      "gear_02": { "type": "_Knob", "label_active": "Mono 12T", "width": 100, "height": 100, "shape": "gear", "arc_width": 5, "indicator_color": "white", "knob_fill_color": "black", "knob_teeth": 12, "gradient_level": 0, "pointer_style": "triangle", "show_ticks": true, "tick_style": "dots" },
      "gear_03": { "type": "_Knob", "label_active": "Mono 24T", "width": 100, "height": 100, "shape": "gear", "arc_width": 5, "indicator_color": "white", "knob_fill_color": "black", "knob_teeth": 24, "gradient_level": 0, "pointer_style": "notch", "show_ticks": true, "tick_style": "numeric" },
      "gear_04": { "type": "_Knob", "label_active": "Mono 6T", "width": 100, "height": 100, "shape": "gear", "arc_width": 5, "indicator_color": "white", "knob_fill_color": "black", "knob_teeth": 6, "gradient_level": 0, "knob_outline_color": "white", "knob_outline_thickness": 2 },
      "gear_05": { "type": "_Knob", "label_active": "Mono Text", "width": 100, "height": 100, "shape": "gear", "arc_width": 5, "indicator_color": "white", "knob_fill_color": "black", "knob_teeth": 16, "gradient_level": 0, "text_inside": true, "no_center": true },
      "gear_06": { "type": "_Knob", "label_active": "Grey 10T", "width": 100, "height": 100, "shape": "gear", "arc_width": 8, "indicator_color": "black", "knob_fill_color": "#808080", "knob_teeth": 10, "gradient_level": 0, "show_ticks": true, "tick_style": "dots" },
      "gear_07": { "type": "_Knob", "label_active": "Red 20T", "width": 100, "height": 100, "shape": "gear", "arc_width": 10, "indicator_color": "white", "knob_fill_color": "#8B0000", "knob_teeth": 20, "gradient_level": 0, "pointer_style": "triangle" },
      "gear_08": { "type": "_Knob", "label_active": "Blue 4T", "width": 100, "height": 100, "shape": "gear", "arc_width": 12, "indicator_color": "white", "knob_fill_color": "#00008B", "knob_teeth": 4, "gradient_level": 0, "pointer_style": "line" },
      "gear_09": { "type": "_Knob", "label_active": "Grn 32T", "width": 100, "height": 100, "shape": "gear", "arc_width": 15, "indicator_color": "black", "knob_fill_color": "#90EE90", "knob_teeth": 32, "gradient_level": 0, "pointer_style": "notch" },
      "gear_10": { "type": "_Knob", "label_active": "Yel 5T", "width": 100, "height": 100, "shape": "gear", "arc_width": 20, "indicator_color": "black", "knob_fill_color": "#FFD700", "knob_teeth": 5, "gradient_level": 0, "text_inside": true },
      "gear_11": { "type": "_Knob", "label_active": "White 8T", "width": 100, "height": 100, "shape": "gear", "arc_width": 5, "indicator_color": "black", "knob_fill_color": "white", "knob_teeth": 8, "gradient_level": 0, "knob_outline_color": "black", "knob_outline_thickness": 2 },
      "gear_12": { "type": "_Knob", "label_active": "Orange 12T", "width": 100, "height": 100, "shape": "gear", "arc_width": 10, "indicator_color": "black", "knob_fill_color": "#FFA500", "knob_teeth": 12, "gradient_level": 0, "show_ticks": true, "tick_style": "simple" },
      "gear_13": { "type": "_Knob", "label_active": "Purp 18T", "width": 100, "height": 100, "shape": "gear", "arc_width": 15, "indicator_color": "white", "knob_fill_color": "#800080", "knob_teeth": 18, "gradient_level": 0, "show_ticks": true, "tick_style": "numeric" },
      "gear_14": { "type": "_Knob", "label_active": "Cyan 9T", "width": 100, "height": 100, "shape": "gear", "arc_width": 20, "indicator_color": "black", "knob_fill_color": "#00FFFF", "knob_teeth": 9, "gradient_level": 0, "pointer_style": "triangle" },
      "gear_15": { "type": "_Knob", "label_active": "Pink 7T", "width": 100, "height": 100, "shape": "gear", "arc_width": 25, "indicator_color": "black", "knob_fill_color": "#FFC0CB", "knob_teeth": 7, "gradient_level": 0, "text_inside": true },
      "gear_16": { "type": "_Knob", "label_active": "M_Line_8", "width": 100, "height": 100, "shape": "gear", "arc_width": 6, "indicator_color": "white", "knob_fill_color": "#2b2b2b", "knob_teeth": 8, "gradient_level": 0, "pointer_style": "line", "knob_outline_color": "white", "knob_outline_thickness": 1 },
      "gear_17": { "type": "_Knob", "label_active": "M_Tri_12", "width": 100, "height": 100, "shape": "gear", "arc_width": 11, "indicator_color": "white", "knob_fill_color": "#2b2b2b", "knob_teeth": 12, "gradient_level": 0, "pointer_style": "triangle", "knob_outline_color": "white", "knob_outline_thickness": 1 },
      "gear_18": { "type": "_Knob", "label_active": "M_Notch_16", "width": 100, "height": 100, "shape": "gear", "arc_width": 16, "indicator_color": "white", "knob_fill_color": "#2b2b2b", "knob_teeth": 16, "gradient_level": 0, "pointer_style": "notch", "knob_outline_color": "white", "knob_outline_thickness": 1 },
      "gear_19": { "type": "_Knob", "label_active": "M_Dot_20", "width": 100, "height": 100, "shape": "gear", "arc_width": 21, "indicator_color": "white", "knob_fill_color": "#2b2b2b", "knob_teeth": 20, "gradient_level": 0, "show_ticks": true, "tick_style": "dots", "knob_outline_color": "white", "knob_outline_thickness": 1 },
      "gear_20": { "type": "_Knob", "label_active": "M_Num_24", "width": 100, "height": 100, "shape": "gear", "arc_width": 26, "indicator_color": "white", "knob_fill_color": "#2b2b2b", "knob_teeth": 24, "gradient_level": 0, "show_ticks": true, "tick_style": "numeric", "knob_outline_color": "white", "knob_outline_thickness": 1 },
      "gear_21": { "type": "_Knob", "label_active": "Tomato 8", "width": 100, "height": 100, "shape": "gear", "arc_width": 7, "indicator_color": "white", "knob_fill_color": "#FF6347", "knob_teeth": 8, "gradient_level": 0, "show_ticks": true, "tick_style": "simple" },
      "gear_22": { "type": "_Knob", "label_active": "Olive 12", "width": 100, "height": 100, "shape": "gear", "arc_width": 13, "indicator_color": "black", "knob_fill_color": "#808000", "knob_teeth": 12, "gradient_level": 0, "show_ticks": true, "tick_style": "dots" },
      "gear_23": { "type": "_Knob", "label_active": "Teal 16", "width": 100, "height": 100, "shape": "gear", "arc_width": 19, "indicator_color": "white", "knob_fill_color": "#008080", "knob_teeth": 16, "gradient_level": 0, "show_ticks": true, "tick_style": "numeric" },
      "gear_24": { "type": "_Knob", "label_active": "Navy 24", "width": 100, "height": 100, "shape": "gear", "arc_width": 24, "indicator_color": "white", "knob_fill_color": "#000080", "knob_teeth": 24, "gradient_level": 0, "pointer_style": "notch" },
      "gear_25": { "type": "_Knob", "label_active": "Maroon 6", "width": 100, "height": 100, "shape": "gear", "arc_width": 29, "indicator_color": "white", "knob_fill_color": "#800000", "knob_teeth": 6, "gradient_level": 0, "pointer_style": "triangle" },
      "gear_26": { "type": "_Knob", "label_active": "Orchid 14", "width": 100, "height": 100, "shape": "gear", "arc_width": 5, "indicator_color": "white", "knob_fill_color": "#BA55D3", "knob_teeth": 14, "gradient_level": 0, "pointer_style": "line" },
      "gear_27": { "type": "_Knob", "label_active": "Pink2 22", "width": 100, "height": 100, "shape": "gear", "arc_width": 9, "indicator_color": "black", "knob_fill_color": "#FF69B4", "knob_teeth": 22, "gradient_level": 0, "pointer_style": "notch" },
      "gear_28": { "type": "_Knob", "label_active": "SpgG 10", "width": 100, "height": 100, "shape": "gear", "arc_width": 14, "indicator_color": "black", "knob_fill_color": "#00FA9A", "knob_teeth": 10, "gradient_level": 0, "pointer_style": "line" },
      "gear_29": { "type": "_Knob", "label_active": "FireB 30", "width": 100, "height": 100, "shape": "gear", "arc_width": 23, "indicator_color": "white", "knob_fill_color": "#B22222", "knob_teeth": 30, "gradient_level": 0, "text_inside": true },
      "gear_30": { "type": "_Knob", "label_active": "Dodg2 18", "width": 100, "height": 100, "shape": "gear", "arc_width": 27, "indicator_color": "white", "knob_fill_color": "#1E90FF", "knob_teeth": 18, "gradient_level": 0, "text_inside": true },
      "gear_31": { "type": "_Knob", "label_active": "Mono Inv 8", "width": 100, "height": 100, "shape": "gear", "arc_width": 6, "indicator_color": "black", "knob_fill_color": "white", "knob_teeth": 8, "gradient_level": 0, "knob_outline_color": "black", "knob_outline_thickness": 2 },
      "gear_32": { "type": "_Knob", "label_active": "Mono Inv 12", "width": 100, "height": 100, "shape": "gear", "arc_width": 12, "indicator_color": "black", "knob_fill_color": "white", "knob_teeth": 12, "gradient_level": 0, "knob_outline_color": "black", "knob_outline_thickness": 2, "pointer_style": "triangle" },
      "gear_33": { "type": "_Knob", "label_active": "Mono Inv 24", "width": 100, "height": 100, "shape": "gear", "arc_width": 18, "indicator_color": "black", "knob_fill_color": "white", "knob_teeth": 24, "gradient_level": 0, "knob_outline_color": "black", "knob_outline_thickness": 2, "pointer_style": "notch" },
      "gear_34": { "type": "_Knob", "label_active": "Khaki 7", "width": 100, "height": 100, "shape": "gear", "arc_width": 22, "indicator_color": "black", "knob_fill_color": "#F0E68C", "knob_teeth": 7, "gradient_level": 0, "knob_outline_color": "brown", "knob_outline_thickness": 2 },
      "gear_35": { "type": "_Knob", "label_active": "PalT 11", "width": 100, "height": 100, "shape": "gear", "arc_width": 28, "indicator_color": "black", "knob_fill_color": "#AFEEEE", "knob_teeth": 11, "gradient_level": 0, "text_inside": true },
      "gear_36": { "type": "_Knob", "label_active": "Plum 9", "width": 100, "height": 100, "shape": "gear", "arc_width": 8, "indicator_color": "white", "knob_fill_color": "#DDA0DD", "knob_teeth": 9, "gradient_level": 0, "pointer_style": "triangle" },
      "gear_37": { "type": "_Knob", "label_active": "PalV 13", "width": 100, "height": 100, "shape": "gear", "arc_width": 11, "indicator_color": "white", "knob_fill_color": "#DB7093", "knob_teeth": 13, "gradient_level": 0, "pointer_style": "notch" },
      "gear_38": { "type": "_Knob", "label_active": "MedS 15", "width": 100, "height": 100, "shape": "gear", "arc_width": 16, "indicator_color": "white", "knob_fill_color": "#3CB371", "knob_teeth": 15, "gradient_level": 0, "pointer_style": "line" },
      "gear_39": { "type": "_Knob", "label_active": "DkR 17", "width": 100, "height": 100, "shape": "gear", "arc_width": 21, "indicator_color": "white", "knob_fill_color": "#8B0000", "knob_teeth": 17, "gradient_level": 0, "knob_outline_color": "red", "knob_outline_thickness": 3 },
      "gear_40": { "type": "_Knob", "label_active": "StlB 19", "width": 100, "height": 100, "shape": "gear", "arc_width": 26, "indicator_color": "white", "knob_fill_color": "#4682B4", "knob_teeth": 19, "gradient_level": 0, "text_inside": true },
      "gear_41": { "type": "_Knob", "label_active": "Sal 21", "width": 100, "height": 100, "shape": "gear", "arc_width": 7, "indicator_color": "black", "knob_fill_color": "#FA8072", "knob_teeth": 21, "gradient_level": 0, "show_ticks": true, "tick_style": "numeric" },
      "gear_42": { "type": "_Knob", "label_active": "YelG 23", "width": 100, "height": 100, "shape": "gear", "arc_width": 13, "indicator_color": "black", "knob_fill_color": "#9ACD32", "knob_teeth": 23, "gradient_level": 0, "show_ticks": true, "tick_style": "dots" },
      "gear_43": { "type": "_Knob", "label_active": "MedB 25", "width": 100, "height": 100, "shape": "gear", "arc_width": 19, "indicator_color": "white", "knob_fill_color": "#0000CD", "knob_teeth": 25, "gradient_level": 0, "show_ticks": true, "tick_style": "simple" },
      "gear_44": { "type": "_Knob", "label_active": "Lem 27", "width": 100, "height": 100, "shape": "gear", "arc_width": 24, "indicator_color": "black", "knob_fill_color": "#FFFACD", "knob_teeth": 27, "gradient_level": 0, "knob_outline_color": "gray", "knob_outline_thickness": 3 },
      "gear_45": { "type": "_Knob", "label_active": "LtS 29", "width": 100, "height": 100, "shape": "gear", "arc_width": 30, "indicator_color": "black", "knob_fill_color": "#20B2AA", "knob_teeth": 29, "gradient_level": 0, "text_inside": true },
      "gear_46": { "type": "_Knob", "label_active": "DkO 31", "width": 100, "height": 100, "shape": "gear", "arc_width": 5, "indicator_color": "white", "knob_fill_color": "#9932CC", "knob_teeth": 31, "gradient_level": 0, "pointer_style": "triangle" },
      "gear_47": { "type": "_Knob", "label_active":"MedV 33", "width": 100, "height": 100, "shape": "gear", "arc_width": 10, "indicator_color": "white", "knob_fill_color": "#C71585", "knob_teeth": 33, "gradient_level": 0, "pointer_style": "notch" },
      "gear_48": { "type": "_Knob", "label_active": "For 35", "width": 100, "height": 100, "shape": "gear", "arc_width": 15, "indicator_color": "white", "knob_fill_color": "#228B22", "knob_teeth": 35, "gradient_level": 0, "pointer_style": "line" },
      "gear_49": { "type": "_Knob", "label_active": "Sie 40", "width": 100, "height": 100, "shape": "gear", "arc_width": 20, "indicator_color": "white", "knob_fill_color": "#A52A2A", "knob_teeth": 40, "gradient_level": 0, "knob_outline_color": "black", "knob_outline_thickness": 2 },
      "gear_50": { "type": "_Knob", "label_active": "SB2 50", "width": 100, "height": 100, "shape": "gear", "arc_width": 25, "indicator_color": "black", "knob_fill_color": "#87CEEB", "knob_teeth": 50, "gradient_level": 0, "text_inside": true }
    }
  }
}
